cmsgov/__init__.py
cmsgov/py.typed
cmsgov/provider_data/__init__.py
cmsgov/provider_data/py.typed
cmsgov/provider_data/v1/__init__.py
cmsgov/provider_data/v1/client.py
cmsgov/provider_data/v1/model.py
cmsgov/provider_data/v1/py.typed
cmsgov-0.0.0a1.dist-info/METADATA
cmsgov-0.0.0a1.dist-info/WHEEL
cmsgov-0.0.0a1.dist-info/RECORD
