Metadata-Version: 2.4
Name: cmsgov
Version: 0.0.0a1
Project-URL: Documentation, https://cmsgov.enorganic.org
Project-URL: Repository, https://github.com/enorganic/cmsgov
Author-email: david@belais.me
License-Expression: MIT
Requires-Python: ~=3.9
Requires-Dist: oapi~=2.4
